fmod_tool/__init__.py
fmod_tool/default_settings.py
fmod_tool/helpers.py
fmod_tool/tool.py
fmod_tool-0.1.10.dist-info/entry_points.txt
fmod_tool-0.1.10.dist-info/LICENSE
fmod_tool-0.1.10.dist-info/WHEEL
fmod_tool-0.1.10.dist-info/METADATA
fmod_tool-0.1.10.dist-info/RECORD
