Metadata-Version: 2.1
Name: fmod-tool
Version: 0.1.10
Summary: A simple tool made to help keep track when correcting exercises for the course "Formale Modellierung"
Home-page: https://github.com/hurbeana/fmod_tool
License: MIT
Keywords: FMOD,correction,assistance,TU Vienna
Author: Hurbean Alexander
Author-email: alexander.hurbean@tuwien.ac.at
Requires-Python: >=3.7.1
Classifier: License :: OSI Approved :: MIT License
Classifier: Programming Language :: Python :: 3
Classifier: Programming Language :: Python :: 3.8
Classifier: Programming Language :: Python :: 3.9
Requires-Dist: PyYAML (>=5.4.1,<6.0.0)
Requires-Dist: click (>=8.0.0,<9.0.0)
Requires-Dist: click-pathlib (>=2020.3.13,<2021.0.0)
Requires-Dist: numpy (>=1.20.3,<2.0.0)
Requires-Dist: openpyxl (>=3.0.7,<4.0.0)
Requires-Dist: pandas (>=1.2.4,<2.0.0)
Requires-Dist: tabulate (>=0.8.9,<0.9.0)
Requires-Dist: xlrd (>=2.0.1,<3.0.0)
Project-URL: Repository, https://github.com/hurbeana/fmod_tool
